MANIFEST.in
README
VERSION
setup.py
icyeye/__init__.py
icyeye/cli.py
icyeye.egg-info/PKG-INFO
icyeye.egg-info/SOURCES.txt
icyeye.egg-info/dependency_links.txt
icyeye.egg-info/entry_points.txt
icyeye.egg-info/not-zip-safe
icyeye.egg-info/requires.txt
icyeye.egg-info/top_level.txt